dir2prompt/__init__.py
dir2prompt/cli.py
dir2prompt/clipboard.py
dir2prompt/main.py
dir2prompts-0.2.2.dist-info/licenses/LICENSE
dir2prompts-0.2.2.dist-info/METADATA
dir2prompts-0.2.2.dist-info/WHEEL
dir2prompts-0.2.2.dist-info/entry_points.txt
dir2prompts-0.2.2.dist-info/top_level.txt
dir2prompts-0.2.2.dist-info/RECORD
