Metadata-Version: 2.4
Name: dir2prompts
Version: 0.2.2
Summary: 一个生成目录树结构的命令行工具
Home-page: https://github.com/Jeffjeno/dir2prompt
Author: WangZhiZhou
Author-email: WangZhiZhou <jenojeff66@gmail.com>
License: MIT License
Project-URL: Homepage, https://github.com/Jeffjeno/dir2prompt
Project-URL: Bug Reports, https://github.com/Jeffjeno/dir2prompt/issues
Project-URL: Source, https://github.com/Jeffjeno/dir2prompt
Keywords: directory,tree,file-structure,command-line
Classifier: Development Status :: 3 - Alpha
Classifier: Intended Audience :: Developers
Classifier: License :: OSI Approved :: MIT License
Classifier: Operating System :: OS Independent
Classifier: Programming Language :: Python :: 3
Classifier: Programming Language :: Python :: 3.7
Classifier: Programming Language :: Python :: 3.8
Classifier: Programming Language :: Python :: 3.9
Classifier: Programming Language :: Python :: 3.10
Classifier: Programming Language :: Python :: 3.11
Classifier: Programming Language :: Python :: 3.12
Requires-Python: >=3.7
License-File: LICENSE
Requires-Dist: pyperclip>=1.8.0
Dynamic: author
Dynamic: home-page
Dynamic: license-file
Dynamic: requires-python
